{
    "classes": [
        {
            "className": "FirmwareUploader",
            "lineNumber": 13,
            "methods": [
                {
                    "access": "public",
                    "index": 24,
                    "name": "refreshPorts",
                    "returnType": "void"
                },
                {
                    "access": "public",
                    "arguments": [
                        {
                            "name": "url",
                            "type": "QUrl"
                        }
                    ],
                    "index": 25,
                    "name": "setFileUrl",
                    "returnType": "void"
                },
                {
                    "access": "public",
                    "index": 26,
                    "name": "openPort",
                    "returnType": "void"
                },
                {
                    "access": "public",
                    "index": 27,
                    "name": "closePort",
                    "returnType": "void"
                },
                {
                    "access": "public",
                    "index": 28,
                    "name": "start",
                    "returnType": "void"
                },
                {
                    "access": "public",
                    "index": 29,
                    "name": "sendVersionFrameManual",
                    "returnType": "void"
                },
                {
                    "access": "public",
                    "index": 30,
                    "name": "sendHeaderManual",
                    "returnType": "void"
                },
                {
                    "access": "public",
                    "index": 31,
                    "name": "sendFirmwareManual",
                    "returnType": "void"
                },
                {
                    "access": "public",
                    "index": 32,
                    "name": "copyHeaderToClipboard",
                    "returnType": "void"
                },
                {
                    "access": "public",
                    "index": 33,
                    "name": "cancel",
                    "returnType": "void"
                },
                {
                    "access": "public",
                    "index": 34,
                    "name": "clearLog",
                    "returnType": "void"
                }
            ],
            "object": true,
            "properties": [
                {
                    "constant": false,
                    "designable": true,
                    "final": false,
                    "index": 0,
                    "name": "ports",
                    "notify": "portsChanged",
                    "read": "ports",
                    "required": false,
                    "scriptable": true,
                    "stored": true,
                    "type": "QVariantList",
                    "user": false
                },
                {
                    "constant": false,
                    "designable": true,
                    "final": false,
                    "index": 1,
                    "name": "portName",
                    "notify": "portNameChanged",
                    "read": "portName",
                    "required": false,
                    "scriptable": true,
                    "stored": true,
                    "type": "QString",
                    "user": false,
                    "write": "setPortName"
                },
                {
                    "constant": false,
                    "designable": true,
                    "final": false,
                    "index": 2,
                    "name": "baudRate",
                    "notify": "baudRateChanged",
                    "read": "baudRate",
                    "required": false,
                    "scriptable": true,
                    "stored": true,
                    "type": "int",
                    "user": false,
                    "write": "setBaudRate"
                },
                {
                    "constant": false,
                    "designable": true,
                    "final": false,
                    "index": 3,
                    "name": "filePath",
                    "notify": "filePathChanged",
                    "read": "filePath",
                    "required": false,
                    "scriptable": true,
                    "stored": true,
                    "type": "QString",
                    "user": false,
                    "write": "setFilePath"
                },
                {
                    "constant": false,
                    "designable": true,
                    "final": false,
                    "index": 4,
                    "name": "fileName",
                    "notify": "fileInfoChanged",
                    "read": "fileName",
                    "required": false,
                    "scriptable": true,
                    "stored": true,
                    "type": "QString",
                    "user": false
                },
                {
                    "constant": false,
                    "designable": true,
                    "final": false,
                    "index": 5,
                    "name": "fileSizeText",
                    "notify": "fileInfoChanged",
                    "read": "fileSizeText",
                    "required": false,
                    "scriptable": true,
                    "stored": true,
                    "type": "QString",
                    "user": false
                },
                {
                    "constant": false,
                    "designable": true,
                    "final": false,
                    "index": 6,
                    "name": "crcHex",
                    "notify": "fileInfoChanged",
                    "read": "crcHex",
                    "required": false,
                    "scriptable": true,
                    "stored": true,
                    "type": "QString",
                    "user": false
                },
                {
                    "constant": false,
                    "designable": true,
                    "final": false,
                    "index": 7,
                    "name": "versionText",
                    "notify": "versionInfoChanged",
                    "read": "versionText",
                    "required": false,
                    "scriptable": true,
                    "stored": true,
                    "type": "QString",
                    "user": false,
                    "write": "setVersionText"
                },
                {
                    "constant": false,
                    "designable": true,
                    "final": false,
                    "index": 8,
                    "name": "versionFlag",
                    "notify": "versionInfoChanged",
                    "read": "versionFlag",
                    "required": false,
                    "scriptable": true,
                    "stored": true,
                    "type": "int",
                    "user": false,
                    "write": "setVersionFlag"
                },
                {
                    "constant": false,
                    "designable": true,
                    "final": false,
                    "index": 9,
                    "name": "versionFrameHex",
                    "notify": "versionInfoChanged",
                    "read": "versionFrameHex",
                    "required": false,
                    "scriptable": true,
                    "stored": true,
                    "type": "QString",
                    "user": false
                },
                {
                    "constant": false,
                    "designable": true,
                    "final": false,
                    "index": 10,
                    "name": "headerHex",
                    "notify": "headerHexChanged",
                    "read": "headerHex",
                    "required": false,
                    "scriptable": true,
                    "stored": true,
                    "type": "QString",
                    "user": false
                },
                {
                    "constant": false,
                    "designable": true,
                    "final": false,
                    "index": 11,
                    "name": "packetSize",
                    "notify": "packetSizeChanged",
                    "read": "packetSize",
                    "required": false,
                    "scriptable": true,
                    "stored": true,
                    "type": "int",
                    "user": false,
                    "write": "setPacketSize"
                },
                {
                    "constant": false,
                    "designable": true,
                    "final": false,
                    "index": 12,
                    "name": "headerDelayMs",
                    "notify": "headerDelayMsChanged",
                    "read": "headerDelayMs",
                    "required": false,
                    "scriptable": true,
                    "stored": true,
                    "type": "int",
                    "user": false,
                    "write": "setHeaderDelayMs"
                },
                {
                    "constant": false,
                    "designable": true,
                    "final": false,
                    "index": 13,
                    "name": "packetDelayMs",
                    "notify": "packetDelayMsChanged",
                    "read": "packetDelayMs",
                    "required": false,
                    "scriptable": true,
                    "stored": true,
                    "type": "int",
                    "user": false,
                    "write": "setPacketDelayMs"
                },
                {
                    "constant": false,
                    "designable": true,
                    "final": false,
                    "index": 14,
                    "name": "progress",
                    "notify": "progressChanged",
                    "read": "progress",
                    "required": false,
                    "scriptable": true,
                    "stored": true,
                    "type": "double",
                    "user": false
                },
                {
                    "constant": false,
                    "designable": true,
                    "final": false,
                    "index": 15,
                    "name": "busy",
                    "notify": "busyChanged",
                    "read": "busy",
                    "required": false,
                    "scriptable": true,
                    "stored": true,
                    "type": "bool",
                    "user": false
                },
                {
                    "constant": false,
                    "designable": true,
                    "final": false,
                    "index": 16,
                    "name": "serialOpen",
                    "notify": "serialOpenChanged",
                    "read": "serialOpen",
                    "required": false,
                    "scriptable": true,
                    "stored": true,
                    "type": "bool",
                    "user": false
                },
                {
                    "constant": false,
                    "designable": true,
                    "final": false,
                    "index": 17,
                    "name": "manualHeaderSent",
                    "notify": "manualHeaderSentChanged",
                    "read": "manualHeaderSent",
                    "required": false,
                    "scriptable": true,
                    "stored": true,
                    "type": "bool",
                    "user": false
                },
                {
                    "constant": false,
                    "designable": true,
                    "final": false,
                    "index": 18,
                    "name": "status",
                    "notify": "statusChanged",
                    "read": "status",
                    "required": false,
                    "scriptable": true,
                    "stored": true,
                    "type": "QString",
                    "user": false
                },
                {
                    "constant": false,
                    "designable": true,
                    "final": false,
                    "index": 19,
                    "name": "logText",
                    "notify": "logTextChanged",
                    "read": "logText",
                    "required": false,
                    "scriptable": true,
                    "stored": true,
                    "type": "QString",
                    "user": false
                }
            ],
            "qualifiedClassName": "FirmwareUploader",
            "signals": [
                {
                    "access": "public",
                    "index": 0,
                    "name": "portsChanged",
                    "returnType": "void"
                },
                {
                    "access": "public",
                    "index": 1,
                    "name": "portNameChanged",
                    "returnType": "void"
                },
                {
                    "access": "public",
                    "index": 2,
                    "name": "baudRateChanged",
                    "returnType": "void"
                },
                {
                    "access": "public",
                    "index": 3,
                    "name": "filePathChanged",
                    "returnType": "void"
                },
                {
                    "access": "public",
                    "index": 4,
                    "name": "fileInfoChanged",
                    "returnType": "void"
                },
                {
                    "access": "public",
                    "index": 5,
                    "name": "versionInfoChanged",
                    "returnType": "void"
                },
                {
                    "access": "public",
                    "index": 6,
                    "name": "headerHexChanged",
                    "returnType": "void"
                },
                {
                    "access": "public",
                    "index": 7,
                    "name": "packetSizeChanged",
                    "returnType": "void"
                },
                {
                    "access": "public",
                    "index": 8,
                    "name": "headerDelayMsChanged",
                    "returnType": "void"
                },
                {
                    "access": "public",
                    "index": 9,
                    "name": "packetDelayMsChanged",
                    "returnType": "void"
                },
                {
                    "access": "public",
                    "index": 10,
                    "name": "progressChanged",
                    "returnType": "void"
                },
                {
                    "access": "public",
                    "index": 11,
                    "name": "busyChanged",
                    "returnType": "void"
                },
                {
                    "access": "public",
                    "index": 12,
                    "name": "serialOpenChanged",
                    "returnType": "void"
                },
                {
                    "access": "public",
                    "index": 13,
                    "name": "manualHeaderSentChanged",
                    "returnType": "void"
                },
                {
                    "access": "public",
                    "index": 14,
                    "name": "statusChanged",
                    "returnType": "void"
                },
                {
                    "access": "public",
                    "index": 15,
                    "name": "logTextChanged",
                    "returnType": "void"
                }
            ],
            "slots": [
                {
                    "access": "private",
                    "index": 16,
                    "name": "sendNextPacket",
                    "returnType": "void"
                },
                {
                    "access": "private",
                    "index": 17,
                    "name": "checkSelectedFile",
                    "returnType": "void"
                },
                {
                    "access": "private",
                    "arguments": [
                        {
                            "name": "data",
                            "type": "QByteArray"
                        }
                    ],
                    "index": 18,
                    "name": "handleSerialReadyRead",
                    "returnType": "void"
                },
                {
                    "access": "private",
                    "arguments": [
                        {
                            "name": "data",
                            "type": "QByteArray"
                        }
                    ],
                    "index": 19,
                    "name": "appendRxLog",
                    "returnType": "void"
                },
                {
                    "access": "private",
                    "index": 20,
                    "name": "handleHandshakeTimeout",
                    "returnType": "void"
                },
                {
                    "access": "private",
                    "arguments": [
                        {
                            "name": "totalBytes",
                            "type": "qint64"
                        },
                        {
                            "name": "tag",
                            "type": "int"
                        }
                    ],
                    "index": 21,
                    "name": "handleWriteFinished",
                    "returnType": "void"
                },
                {
                    "access": "private",
                    "arguments": [
                        {
                            "name": "error",
                            "type": "int"
                        },
                        {
                            "name": "message",
                            "type": "QString"
                        }
                    ],
                    "index": 22,
                    "name": "handleSerialError",
                    "returnType": "void"
                },
                {
                    "access": "private",
                    "arguments": [
                        {
                            "name": "tag",
                            "type": "int"
                        }
                    ],
                    "index": 23,
                    "name": "handleWriteTimeout",
                    "returnType": "void"
                }
            ],
            "superClasses": [
                {
                    "access": "public",
                    "name": "QObject"
                }
            ]
        }
    ],
    "inputFile": "FirmwareUploader.h",
    "outputRevision": 68
}
